gwspy/__init__.py
gwspy/__main__.py
gwspy/_auth.py
gwspy/coastlines.py
gwspy/geometry_utils.py
gwspy/gplates.py
gwspy/paleoearth.py
gwspy/plate_model.py
gwspy/quaternions.py
gwspy/reconstruction.py
gwspy/resample_line.py
gwspy/rotation.py
gwspy/spherical_triangle.py
gwspy/subduction_teeth.py
gwspy/topology.py
gwspy/utils.py
gwspy/examples/make_paleo_coastlines_movie.py
gwspy/examples/paleo-coastlines.ipynb
gwspy/examples/plot_paleo_cities.py
gwspy/examples/plot_paleo_coastlines.py
gwspy/examples/plot_paleo_labels.py
gwspy/examples/plot_subduction_zones.py
gwspy/examples/plot_topological_features.py
gwspy/examples/plot_topological_plate_boundaries.py
gwspy/examples/plot_topological_plate_polygons.py
gwspy/examples/reconstruct_shapely_points.py
gwspy-0.1.2.dist-info/LICENSE
gwspy-0.1.2.dist-info/METADATA
gwspy-0.1.2.dist-info/WHEEL
gwspy-0.1.2.dist-info/entry_points.txt
gwspy-0.1.2.dist-info/top_level.txt
gwspy-0.1.2.dist-info/RECORD
