Metadata-Version: 2.1
Name: gwspy
Version: 0.1.2
Summary: GPlates Web Service Python client/proxy
Author-email: Michael Chin <michael.chin@sydney.edu.au>
License: MIT License
Project-URL: Homepage, https://github.com/michaelchin/gplates-python-proxy
Keywords: GPlates,RESTful,Web Service,Plate Tectonics
Classifier: License :: OSI Approved :: MIT License
Classifier: Programming Language :: Python
Classifier: Programming Language :: Python :: 3
Requires-Python: >=3.9
License-File: LICENSE
Requires-Dist: python-dotenv
Requires-Dist: requests
Provides-Extra: dev
Requires-Dist: black ; extra == 'dev'
Requires-Dist: bumpver ; extra == 'dev'
Requires-Dist: isort ; extra == 'dev'
Requires-Dist: pip-tools ; extra == 'dev'
Requires-Dist: pytest ; extra == 'dev'
